__init__.py
cli.py
error.py
interpreter.py
lexer.py
parser_.py
q.py
stdlib.py
symbol_table.py
values.py
qlang-0.1.4.dist-info/LICENSE
qlang-0.1.4.dist-info/METADATA
qlang-0.1.4.dist-info/WHEEL
qlang-0.1.4.dist-info/top_level.txt
qlang-0.1.4.dist-info/RECORD
