Metadata-Version: 2.1
Name: qlang
Version: 0.1.4
Summary: A concise, procedural programming language
Home-page: https://github.com/nirvanasupermind/qlang
Author: nirvanasupermind
Author-email: nirvana.supermind@gmail.com
License: LICENSE
Platform: UNKNOWN
